notion_client/__init__.py
notion_client/api_endpoints.py
notion_client/client.py
notion_client/errors.py
notion_client/helpers.py
notion_client/logging.py
notion_client/py.typed
notion_client/typing.py
notion_client-2.6.0.dist-info/licenses/LICENSE
notion_client-2.6.0.dist-info/METADATA
notion_client-2.6.0.dist-info/WHEEL
notion_client-2.6.0.dist-info/top_level.txt
notion_client-2.6.0.dist-info/RECORD
