Metadata-Version: 2.4
Name: notion-client
Version: 2.6.0
Summary: Python client for the official Notion API
Home-page: https://github.com/ramnes/notion-sdk-py
Author: Guillaume Gelin
Author-email: contact@ramnes.eu
Classifier: Programming Language :: Python :: 3.8
Classifier: Programming Language :: Python :: 3.9
Classifier: Programming Language :: Python :: 3.10
Classifier: Programming Language :: Python :: 3.11
Classifier: Programming Language :: Python :: 3.12
Classifier: Programming Language :: Python :: 3.13
Classifier: Development Status :: 5 - Production/Stable
Classifier: License :: OSI Approved :: MIT License
Requires-Python: >=3.8, <4
License-File: LICENSE
Requires-Dist: httpx>=0.23.0
Dynamic: author
Dynamic: author-email
Dynamic: classifier
Dynamic: description
Dynamic: description-content-type
Dynamic: home-page
Dynamic: license-file
Dynamic: requires-dist
Dynamic: requires-python
Dynamic: summary
